django_prefetch_utils/__init__.py
django_prefetch_utils/apps.py
django_prefetch_utils/backport.py
django_prefetch_utils/selector.py
django_prefetch_utils/descriptors/__init__.py
django_prefetch_utils/descriptors/annotation.py
django_prefetch_utils/descriptors/base.py
django_prefetch_utils/descriptors/equal_fields.py
django_prefetch_utils/descriptors/top_child.py
django_prefetch_utils/descriptors/via_lookup.py
django_prefetch_utils/identity_map/__init__.py
django_prefetch_utils/identity_map/maps.py
django_prefetch_utils/identity_map/persistent.py
django_prefetch_utils/identity_map/wrappers.py
django_prefetch_utils-0.2.0.dist-info/AUTHORS.rst
django_prefetch_utils-0.2.0.dist-info/LICENSE
django_prefetch_utils-0.2.0.dist-info/METADATA
django_prefetch_utils-0.2.0.dist-info/WHEEL
django_prefetch_utils-0.2.0.dist-info/top_level.txt
django_prefetch_utils-0.2.0.dist-info/RECORD
