Metadata-Version: 2.1
Name: django-prefetch-utils
Version: 0.2.0
Summary: An library of utilities and enhancements for Django's prefetch_related system.
Home-page: https://github.com/roverdotcom/django-prefetch-utils
Author: Mike Hansen
Author-email: mike@rover.com
License: BSD 3-Clause License
Platform: UNKNOWN
Classifier: Development Status :: 5 - Production/Stable
Classifier: Intended Audience :: Developers
Classifier: License :: OSI Approved :: BSD License
Classifier: Operating System :: Unix
Classifier: Operating System :: POSIX
Classifier: Operating System :: Microsoft :: Windows
Classifier: Programming Language :: Python
Classifier: Programming Language :: Python :: 3
Classifier: Programming Language :: Python :: 3.7
Classifier: Programming Language :: Python :: 3.8
Classifier: Programming Language :: Python :: 3.9
Classifier: Programming Language :: Python :: 3.10
Classifier: Programming Language :: Python :: Implementation :: CPython
Classifier: Programming Language :: Python :: Implementation :: PyPy
Classifier: Topic :: Utilities
Requires-Dist: django (>=2.2)
Requires-Dist: wrapt (>=1.11)
